{
    "https://informburo.kz/novosti/mart-2023-goda-budet-teplee-cem-obycno-kazgidromet-predstavil-prognoz-pogody-na-mesyac": {
        "link_name": "Март 2023 года будет теплее, чем обычно. \"Казгидромет\" представил прогноз погоды на месяц",
        "views": "11649",
        "publ_time": "1 марта 2023, 23:07",
        "topic": "#назаметку"
    },
    "https://informburo.kz/novosti/na-severe-kazaxstana-agrariyam-vydelyali-diztoplivo-bez-ucyota-klimata": {
        "link_name": "На севере Казахстана аграриям выделяли дизтопливо без учёта климата",
        "views": "491",
        "publ_time": "1 марта 2023, 22:07",
        "topic": "#официально"
    },
    "https://informburo.kz/novosti/v-kazaxstane-nacali-priyom-dokumentov-dlya-lgotnogo-mikrokreditovaniya-molodyozi": {
        "link_name": "В Казахстане начали приём документов для льготного микрокредитования молодёжи",
        "views": "23365",
        "publ_time": "1 марта 2023, 21:10",
        "topic": "#назаметку"
    },
    "https://informburo.kz/novosti/prognoz-pogody-na-2-marta-v-astane-i-devyati-oblastyax-obyavleno-stormovoe-preduprezdenie": {
        "link_name": "Прогноз погоды на 2 марта: в Астане и девяти областях объявлено штормовое предупреждение",
        "views": "14466",
        "publ_time": "1 марта 2023, 21:00",
        "topic": "#назаметку"
    },
    "https://informburo.kz/novosti/cto-proisxodit-v-ukraine-glavnoe-za-den-1-marta": {
        "link_name": "Что происходит в Украине. Главное за день 1 марта",
        "views": "2281",
        "publ_time": "1 марта 2023, 20:40",
        "topic": "#неонас"
    },
    "https://informburo.kz/novosti/krupnye-kompanii-saudovskoi-aravii-postroyat-vetrovuyu-elektrostanciyu-v-1-gvt-v-zetysuskoi-oblasti": {
        "link_name": "Крупные компании Саудовской Аравии построят ветровую электростанцию в 1 ГВт в Жетысуской области",
        "views": "956",
        "publ_time": "1 марта 2023, 20:30",
        "topic": "#официально"
    },
    "https://informburo.kz/novosti/v-zamerzayushhix-skolax-ekibastuza-ustanovili-konvektornye-sistemy-otopleniya": {
        "link_name": "В замерзающих школах Экибастуза установили конвекторные системы отопления",
        "views": "730",
        "publ_time": "1 марта 2023, 19:39",
        "topic": "#официально"
    },
    "https://informburo.kz/novosti/parlament-finlyandii-progolosoval-za-vstuplenie-strany-v-nato": {
        "link_name": "Парламент Финляндии проголосовал за вступление страны в НАТО",
        "views": "203",
        "publ_time": "1 марта 2023, 19:00",
        "topic": "#неонас"
    },
    "https://informburo.kz/novosti/sotrudnice-ktz-obvinyonnoi-v-xishhenii-82-mln-tenge-vynesli-prigovor": {
        "link_name": "Сотруднице КТЖ, обвинённой в хищении 82 млн тенге, вынесли приговор",
        "views": "3067",
        "publ_time": "1 марта 2023, 18:41",
        "topic": "#цифра"
    },
    "https://informburo.kz/novosti/kak-naiti-svoi-izbiratelnyi-okrug-i-ucastok-dlya-golosovaniya-na-vyborax-v-mazilis-i-maslixat-almaty": {
        "link_name": "Как найти свой избирательный округ и участок для голосования на выборах в мажилис и маслихат Алматы",
        "views": "1617",
        "publ_time": "1 марта 2023, 18:21",
        "topic": "#назаметку"
    },
    "https://informburo.kz/novosti/perecislit-dengi-za-proezd-po-platnym-trassam-kazaxstana-mozno-budet-v-tecenie-nedeli": {
        "link_name": "Перечислить деньги за проезд по платным трассам Казахстана можно будет в течение недели",
        "views": "574",
        "publ_time": "1 марта 2023, 18:09",
        "topic": "#назаметку"
    },
    "https://informburo.kz/novosti/nacbank-ustanovil-oficialnyj-kurs-rublya-v-kazahstane-na-2-marta": {
        "link_name": "Нацбанк установил официальный курс рубля в Казахстане на 2 марта",
        "views": "881",
        "publ_time": "1 марта 2023, 17:57",
        "topic": "#назаметку"
    },
    "https://informburo.kz/novosti/kazaxstancy-smogut-zaregistrirovat-osi-cerez-prilozenie": {
        "link_name": "Казахстанцы смогут зарегистрировать ОСИ через приложение",
        "views": "1024",
        "publ_time": "1 марта 2023, 17:52",
        "topic": "#назаметку"
    },
    "https://informburo.kz/novosti/evropeiskoe-kosmiceskoe-agentstvo-namereno-prisvoit-lune-otdelnyi-casovoi-poyas": {
        "link_name": "Европейское космическое агентство намерено присвоить Луне отдельный часовой пояс",
        "views": "96",
        "publ_time": "1 марта 2023, 17:47",
        "topic": "#кстати"
    },
    "https://informburo.kz/novosti/bolee-cem-3000-soldat-polucili-otsrocku-platezei-po-zaimam-iz-za-srocnoi-sluzby": {
        "link_name": "Более чем 3000 солдат получили отсрочку платежей по займам из-за срочной службы",
        "views": "243",
        "publ_time": "1 марта 2023, 17:42",
        "topic": "#цифра"
    },
    "https://informburo.kz/novosti/semero-dacnikov-iz-novoi-buxtarmy-otkazalis-obmenyat-svoi-ucastki-dlya-stroiki-plyaza": {
        "link_name": "Семеро дачников из Новой Бухтармы отказались обменять свои участки для стройки пляжа",
        "views": "12067",
        "publ_time": "1 марта 2023, 17:24",
        "topic": "#кстати"
    },
    "https://informburo.kz/novosti/vtoruyu-partiyu-kazahstanskoj-nefti-postavyat-v-germaniyu-v-marte": {
        "link_name": "Вторую партию казахстанской нефти поставят в Германию в марте",
        "views": "283",
        "publ_time": "1 марта 2023, 17:19",
        "topic": "#официально"
    },
    "https://informburo.kz/novosti/poholodanie-i-osadki-prognoziruet-kazgidromet-v-blizhajshie-dni": {
        "link_name": "Похолодание и осадки прогнозирует Казгидромет в ближайшие дни",
        "views": "6366",
        "publ_time": "1 марта 2023, 17:03",
        "topic": "#назаметку"
    },
    "https://informburo.kz/novosti/vybory-v-maslixat-almaty-bagdata-manzorova-snyali-s-gonki": {
        "link_name": "Выборы в маслихат Алматы: Багдата Манзорова сняли с гонки",
        "views": "1666",
        "publ_time": "1 марта 2023, 16:54",
        "topic": "#официально"
    },
    "https://informburo.kz/novosti/partiya-amanat-akcentiruet-vnimanie-na-ulucsenii-kacestva-dorog-v-kostanaiskoi-oblasti": {
        "link_name": "Партия Amanat акцентирует внимание на улучшении качества дорог в Костанайской области",
        "views": "211",
        "publ_time": "1 марта 2023, 16:31",
        "topic": "#Выборы-2023"
    },
    "https://informburo.kz/novosti/tokaev-nagradil-likvidatorov-avarii-na-tec-v-ekibastuze": {
        "link_name": "Токаев наградил ликвидаторов аварии на ТЭЦ в Экибастузе",
        "views": "3973",
        "publ_time": "1 марта 2023, 16:26",
        "topic": "#официально"
    },
    "https://informburo.kz/novosti/podavali-feikovye-obyavleniya-desyatki-almatincev-stali-zertvami-dvux-mosennikov-iz-zambylskoi-oblasti": {
        "link_name": "\"Подавали фейковые объявления\". Десятки алматинцев стали жертвами двух мошенников из Жамбылской области",
        "views": "1233",
        "publ_time": "1 марта 2023, 16:15",
        "topic": "#назаметку"
    },
    "https://informburo.kz/novosti/opublikovan-spisok-obladatelei-stipendii-bolasak-v-nyom-25-celovek": {
        "link_name": "Опубликован список обладателей стипендии \"Болашак\", в нём 25 человек",
        "views": "1262",
        "publ_time": "1 марта 2023, 15:41",
        "topic": "#официально"
    },
    "https://informburo.kz/novosti/kurs-dollara-upal-eshyo-na-3-5-tenge-na-birzhe": {
        "link_name": "Курс доллара упал ещё на 3,5 тенге на бирже",
        "views": "1509",
        "publ_time": "1 марта 2023, 15:36",
        "topic": "#назаметку"
    }
}